{
	"title": "AFK Detector",
	"description": "Detect, announce, and label players who are away from their Keyboards",
	"description_short": "Detect, announce, and label players who are away from their Keyboards",
	"youtube": null,
	"list_on_site": true,
	"features": [
		{
			"label": "Announces players who have not moved in 10 minutes as away from their keyboards"
		},
		{
			"label": "Attaches AFK prefix to players who are away from their keyboards"
		},
		{
			"label": "Optional team configurations to functionality with pre-establised in-game teams"
		}
	],
	"downloads": [
		{
			"label": "Download for 1.16",
			"file": null
		}
	]
}